<?xml version="1.0"?>
<!DOCTYPE hibernate-mapping PUBLIC "-//Hibernate/Hibernate Mapping DTD 3.0//EN"
"http://www.hibernate.org/dtd/hibernate-mapping-3.0.dtd">
<!-- Generated Jun 16, 2017 10:22:39 AM by Hibernate Tools 4.3.1 -->
<hibernate-mapping>
    <class name="pojo.Resume" table="Resume" schema="dbo" catalog="JobManagement" optimistic-lock="version">
        <id name="resumeId" type="int">
            <column name="ResumeId" />
            <generator class="assigned" />
        </id>
        <many-to-one name="student" class="pojo.Student" fetch="select">
            <column name="StudentId" />
        </many-to-one>
        <property name="resumeName" type="string">
            <column name="ResumeName" length="10" />
        </property>
        <property name="gender" type="java.lang.Character">
            <column name="Gender" length="1" />
        </property>
        <property name="age" type="java.lang.Integer">
            <column name="Age" />
        </property>
        <property name="picPath" type="string">
            <column name="PicPath" length="100" />
        </property>
        <property name="education" type="string">
            <column name="Education" length="20" />
        </property>
        <property name="phone" type="string">
            <column name="Phone" length="20" />
        </property>
        <property name="email" type="string">
            <column name="Email" length="30" />
        </property>
        <property name="skills" type="string">
            <column name="Skills" length="500" />
        </property>
        <property name="expectedJob" type="string">
            <column name="ExpectedJob" length="30" />
        </property>
    </class>
</hibernate-mapping>
